msk_modelling_python/__init__.py
msk_modelling_python/bops.py
msk_modelling_python/classes.py
msk_modelling_python/osimRun.py
msk_modelling_python/utils.py
msk_modelling_python/opensim/__init__.py
msk_modelling_python/opensim/actuators.py
msk_modelling_python/opensim/analyses.py
msk_modelling_python/opensim/common.py
msk_modelling_python/opensim/examplecomponents.py
msk_modelling_python/opensim/moco.py
msk_modelling_python/opensim/report.py
msk_modelling_python/opensim/simbody.py
msk_modelling_python/opensim/simulation.py
msk_modelling_python/opensim/tools.py
msk_modelling_python/opensim/version.py
msk_modelling_python/src/__init__.py
msk_modelling_python/src/classes/__init__.py
msk_modelling_python/src/manuscript/__init__.py
msk_modelling_python/src/manuscript/pdf_comments_to_word.py
msk_modelling_python/src/manuscript/scrape_reference_from_NCBI.py
msk_modelling_python/src/mri/__init__.py
msk_modelling_python/src/mri/compare_coverage_centre_edge_angle.py
msk_modelling_python/src/mri/coverage.py
msk_modelling_python/src/mri/fit_sphere.py
msk_modelling_python/src/mri/gui.py
msk_modelling_python/src/mri/method_sangeux_2015.py
msk_modelling_python/src/mri/multi_fit_sphere.py
msk_modelling_python/src/mri/planes_vectors.py
msk_modelling_python/src/mri/print_coverages.py
msk_modelling_python/src/mri/print_cube.py
msk_modelling_python/src/mri/slicer_bops.py
msk_modelling_python/src/mri/txt_to_csv_coverage.py
msk_modelling_python/src/mri/hip_project/__init__.py
msk_modelling_python/src/mri/hip_project/calculate_covered_area.py
msk_modelling_python/src/mri/hip_project/remesh.py
msk_modelling_python/src/mri/hip_project/rename_files.py
msk_modelling_python/src/mri/hip_project/template_cover_sphere.py
msk_modelling_python/src/muscle_modelling/__init__.py
msk_modelling_python/src/muscle_modelling/calculate_joint_centres.py
msk_modelling_python/src/muscle_modelling/fatigue_model.py
msk_modelling_python/src/muscle_modelling/hypertrophy.py
msk_modelling_python-0.3.1.dist-info/LICENSE.md
msk_modelling_python-0.3.1.dist-info/METADATA
msk_modelling_python-0.3.1.dist-info/WHEEL
msk_modelling_python-0.3.1.dist-info/top_level.txt
msk_modelling_python-0.3.1.dist-info/RECORD
