Metadata-Version: 2.1
Name: msk-modelling-python
Version: 0.3.1
Summary: A Python package for musculoskeletal modelling
Home-page: https://github.com/your_username/msk_modelling_python
Author: Bas
Author-email: basilio.goncalves7@gmail.com
License: UNKNOWN
Platform: UNKNOWN
Classifier: Programming Language :: Python :: 3
Classifier: License :: OSI Approved :: MIT License
Classifier: Operating System :: OS Independent
Requires-Python: >=3.7
Requires-Dist: numpy
Requires-Dist: numpy-stl
